{
  "annotations": {
    "list": [
      {
        "builtIn": 1,
        "datasource": {
          "type": "grafana",
          "uid": "-- Grafana --"
        },
        "enable": true,
        "hide": true,
        "iconColor": "rgba(0, 211, 255, 1)",
        "name": "Annotations & Alerts",
        "type": "dashboard"
      }
    ]
  },
  "editable": true,
  "fiscalYearStartMonth": 0,
  "graphTooltip": 2,
  "id": 1,
  "links": [],
  "panels": [
    {
      "datasource": {
        "type": "influxdb",
        "uid": "bdr06l9c4j474b"
      },
      "fieldConfig": {
        "defaults": {
          "color": {
            "mode": "palette-classic"
          },
          "custom": {
            "axisBorderShow": false,
            "axisCenteredZero": false,
            "axisColorMode": "text",
            "axisLabel": "",
            "axisPlacement": "auto",
            "barAlignment": 0,
            "drawStyle": "line",
            "fillOpacity": 0,
            "gradientMode": "none",
            "hideFrom": {
              "legend": false,
              "tooltip": false,
              "viz": false
            },
            "insertNulls": false,
            "lineInterpolation": "linear",
            "lineWidth": 1,
            "pointSize": 5,
            "scaleDistribution": {
              "type": "linear"
            },
            "showPoints": "auto",
            "spanNulls": false,
            "stacking": {
              "group": "A",
              "mode": "none"
            },
            "thresholdsStyle": {
              "mode": "off"
            }
          },
          "mappings": [],
          "thresholds": {
            "mode": "absolute",
            "steps": [
              {
                "color": "green",
                "value": null
              },
              {
                "color": "red",
                "value": 80
              }
            ]
          }
        },
        "overrides": [
          {
            "matcher": {
              "id": "byName",
              "options": "apparentTemperature"
            },
            "properties": [
              {
                "id": "displayName",
                "value": "Apparent temperature"
              },
              {
                "id": "unit",
                "value": "celsius"
              }
            ]
          },
          {
            "matcher": {
              "id": "byName",
              "options": "cloudCover"
            },
            "properties": [
              {
                "id": "displayName",
                "value": "Cloud cover"
              },
              {
                "id": "unit",
                "value": "percent"
              }
            ]
          },
          {
            "matcher": {
              "id": "byName",
              "options": "humidity"
            },
            "properties": [
              {
                "id": "displayName",
                "value": "Humidity"
              },
              {
                "id": "unit",
                "value": "percent"
              }
            ]
          },
          {
            "matcher": {
              "id": "byName",
              "options": "precipitation_probability"
            },
            "properties": [
              {
                "id": "displayName",
                "value": "Precipitation probability"
              },
              {
                "id": "unit",
                "value": "percent"
              }
            ]
          },
          {
            "matcher": {
              "id": "byName",
              "options": "rain"
            },
            "properties": [
              {
                "id": "displayName",
                "value": "Rain"
              },
              {
                "id": "unit",
                "value": "lengthmm"
              }
            ]
          },
          {
            "matcher": {
              "id": "byName",
              "options": "showers"
            },
            "properties": [
              {
                "id": "displayName",
                "value": "Showers"
              },
              {
                "id": "unit",
                "value": "lengthmm"
              }
            ]
          },
          {
            "matcher": {
              "id": "byName",
              "options": "temperature"
            },
            "properties": [
              {
                "id": "displayName",
                "value": "Temperature"
              },
              {
                "id": "unit",
                "value": "celsius"
              }
            ]
          },
          {
            "matcher": {
              "id": "byName",
              "options": "uvIndex"
            },
            "properties": [
              {
                "id": "displayName",
                "value": "UV Index"
              }
            ]
          },
          {
            "matcher": {
              "id": "byName",
              "options": "visibility"
            },
            "properties": [
              {
                "id": "displayName",
                "value": "Visibility"
              },
              {
                "id": "unit",
                "value": "lengthkm"
              }
            ]
          },
          {
            "matcher": {
              "id": "byName",
              "options": "windDirection"
            },
            "properties": [
              {
                "id": "displayName",
                "value": "Wind direction"
              },
              {
                "id": "unit",
                "value": "degree"
              }
            ]
          },
          {
            "matcher": {
              "id": "byName",
              "options": "windSpeed"
            },
            "properties": [
              {
                "id": "displayName",
                "value": "Wind speed"
              },
              {
                "id": "unit",
                "value": "velocitykmh"
              }
            ]
          }
        ]
      },
      "gridPos": {
        "h": 16,
        "w": 12,
        "x": 0,
        "y": 0
      },
      "id": 28,
      "options": {
        "legend": {
          "calcs": [
            "lastNotNull",
            "min",
            "max",
            "mean"
          ],
          "displayMode": "table",
          "placement": "bottom",
          "showLegend": true
        },
        "tooltip": {
          "maxHeight": 600,
          "mode": "multi",
          "sort": "none"
        }
      },
      "pluginVersion": "11.0.0",
      "targets": [
        {
          "datasource": {
            "type": "influxdb",
            "uid": "bdr06l9c4j474b"
          },
          "query": "from(bucket: \"weather\")\r\n  |> range(start: v.timeRangeStart, stop: v.timeRangeStop)\r\n  |> filter(fn: (r) => r[\"_measurement\"] == \"hourly_weather\")\r\n  |> aggregateWindow(every: v.windowPeriod, fn: mean, createEmpty: false)\r\n  |> yield(name: \"mean\")",
          "refId": "A"
        }
      ],
      "timeFrom": "24h",
      "title": "Forecast",
      "type": "timeseries"
    },
    {
      "datasource": {
        "type": "influxdb",
        "uid": "bdr06l9c4j474b"
      },
      "fieldConfig": {
        "defaults": {
          "color": {
            "mode": "thresholds"
          },
          "mappings": [],
          "thresholds": {
            "mode": "absolute",
            "steps": [
              {
                "color": "green",
                "value": null
              },
              {
                "color": "yellow",
                "value": 30
              },
              {
                "color": "red",
                "value": 35
              }
            ]
          },
          "unit": "celsius"
        },
        "overrides": []
      },
      "gridPos": {
        "h": 4,
        "w": 4,
        "x": 12,
        "y": 0
      },
      "id": 1,
      "options": {
        "colorMode": "value",
        "graphMode": "none",
        "justifyMode": "center",
        "orientation": "auto",
        "reduceOptions": {
          "calcs": [
            "last"
          ],
          "fields": "",
          "values": false
        },
        "showPercentChange": false,
        "textMode": "auto",
        "wideLayout": true
      },
      "pluginVersion": "11.0.0",
      "targets": [
        {
          "datasource": {
            "type": "influxdb",
            "uid": "bdr06l9c4j474b"
          },
          "query": "from(bucket: \"weather\")\r\n  |> range(start: v.timeRangeStart, stop: v.timeRangeStop)\r\n  |> filter(fn: (r) => r[\"_measurement\"] == \"current_weather\")\r\n  |> filter(fn: (r) => r[\"_field\"] == \"temperature\")\r\n  |> aggregateWindow(every: v.windowPeriod, fn: last, createEmpty: false)\r\n  |> yield(name: \"last\")",
          "refId": "A"
        }
      ],
      "title": "Temperature",
      "type": "stat"
    },
    {
      "datasource": {
        "type": "influxdb",
        "uid": "bdr06l9c4j474b"
      },
      "fieldConfig": {
        "defaults": {
          "color": {
            "mode": "thresholds"
          },
          "mappings": [],
          "thresholds": {
            "mode": "absolute",
            "steps": [
              {
                "color": "green",
                "value": null
              },
              {
                "color": "yellow",
                "value": 30
              },
              {
                "color": "red",
                "value": 40
              }
            ]
          },
          "unit": "celsius"
        },
        "overrides": []
      },
      "gridPos": {
        "h": 4,
        "w": 4,
        "x": 16,
        "y": 0
      },
      "id": 3,
      "options": {
        "colorMode": "value",
        "graphMode": "none",
        "justifyMode": "center",
        "orientation": "auto",
        "reduceOptions": {
          "calcs": [
            "lastNotNull"
          ],
          "fields": "",
          "values": false
        },
        "showPercentChange": false,
        "textMode": "auto",
        "wideLayout": true
      },
      "pluginVersion": "11.0.0",
      "targets": [
        {
          "datasource": {
            "type": "influxdb",
            "uid": "bdr06l9c4j474b"
          },
          "query": "from(bucket: \"weather\")\r\n  |> range(start: v.timeRangeStart, stop: v.timeRangeStop)\r\n  |> filter(fn: (r) => r[\"_measurement\"] == \"current_weather\")\r\n  |> filter(fn: (r) => r[\"_field\"] == \"apparentTemperature\")\r\n  |> aggregateWindow(every: v.windowPeriod, fn: last, createEmpty: false)\r\n  |> yield(name: \"last\")",
          "refId": "A"
        }
      ],
      "title": "Apparent temperature",
      "type": "stat"
    },
    {
      "datasource": {
        "type": "influxdb",
        "uid": "bdr06l9c4j474b"
      },
      "fieldConfig": {
        "defaults": {
          "color": {
            "mode": "thresholds"
          },
          "mappings": [],
          "thresholds": {
            "mode": "absolute",
            "steps": [
              {
                "color": "yellow",
                "value": null
              },
              {
                "color": "green",
                "value": 40
              },
              {
                "color": "blue",
                "value": 60
              }
            ]
          },
          "unit": "humidity"
        },
        "overrides": []
      },
      "gridPos": {
        "h": 4,
        "w": 4,
        "x": 20,
        "y": 0
      },
      "id": 4,
      "options": {
        "colorMode": "value",
        "graphMode": "none",
        "justifyMode": "center",
        "orientation": "auto",
        "reduceOptions": {
          "calcs": [
            "lastNotNull"
          ],
          "fields": "",
          "values": false
        },
        "showPercentChange": false,
        "textMode": "auto",
        "wideLayout": true
      },
      "pluginVersion": "11.0.0",
      "targets": [
        {
          "datasource": {
            "type": "influxdb",
            "uid": "bdr06l9c4j474b"
          },
          "query": "from(bucket: \"weather\")\r\n  |> range(start: v.timeRangeStart, stop: v.timeRangeStop)\r\n  |> filter(fn: (r) => r[\"_measurement\"] == \"current_weather\")\r\n  |> filter(fn: (r) => r[\"_field\"] == \"humidity\")\r\n  |> aggregateWindow(every: v.windowPeriod, fn: last, createEmpty: false)\r\n  |> yield(name: \"last\")",
          "refId": "A"
        }
      ],
      "title": "Humidity",
      "type": "stat"
    },
    {
      "datasource": {
        "type": "influxdb",
        "uid": "bdr06l9c4j474b"
      },
      "fieldConfig": {
        "defaults": {
          "color": {
            "mode": "thresholds"
          },
          "mappings": [],
          "thresholds": {
            "mode": "absolute",
            "steps": [
              {
                "color": "green",
                "value": null
              }
            ]
          },
          "unit": "percent"
        },
        "overrides": []
      },
      "gridPos": {
        "h": 4,
        "w": 4,
        "x": 12,
        "y": 4
      },
      "hideTimeOverride": true,
      "id": 26,
      "options": {
        "colorMode": "value",
        "graphMode": "none",
        "justifyMode": "center",
        "orientation": "auto",
        "reduceOptions": {
          "calcs": [
            "lastNotNull"
          ],
          "fields": "",
          "values": false
        },
        "showPercentChange": false,
        "textMode": "auto",
        "wideLayout": true
      },
      "pluginVersion": "11.0.0",
      "targets": [
        {
          "datasource": {
            "type": "influxdb",
            "uid": "bdr06l9c4j474b"
          },
          "query": "from(bucket: \"weather\")\r\n  |> range(start: v.timeRangeStart, stop: v.timeRangeStop)\r\n  |> filter(fn: (r) => r[\"_measurement\"] == \"hourly_weather\")\r\n  |> filter(fn: (r) => r[\"_field\"] == \"precipitation_probability\")\r\n  |> aggregateWindow(every: v.windowPeriod, fn: last, createEmpty: false)\r\n  |> yield(name: \"last\")",
          "refId": "A"
        }
      ],
      "timeFrom": "1h",
      "title": "Precipitation probability",
      "type": "stat"
    },
    {
      "datasource": {
        "type": "influxdb",
        "uid": "bdr06l9c4j474b"
      },
      "fieldConfig": {
        "defaults": {
          "color": {
            "mode": "thresholds"
          },
          "mappings": [],
          "thresholds": {
            "mode": "absolute",
            "steps": [
              {
                "color": "green",
                "value": null
              }
            ]
          },
          "unit": "lengthkm"
        },
        "overrides": []
      },
      "gridPos": {
        "h": 4,
        "w": 4,
        "x": 16,
        "y": 4
      },
      "hideTimeOverride": true,
      "id": 27,
      "options": {
        "colorMode": "value",
        "graphMode": "none",
        "justifyMode": "center",
        "orientation": "auto",
        "reduceOptions": {
          "calcs": [
            "lastNotNull"
          ],
          "fields": "",
          "values": false
        },
        "showPercentChange": false,
        "textMode": "auto",
        "wideLayout": true
      },
      "pluginVersion": "11.0.0",
      "targets": [
        {
          "datasource": {
            "type": "influxdb",
            "uid": "bdr06l9c4j474b"
          },
          "query": "from(bucket: \"weather\")\r\n  |> range(start: v.timeRangeStart, stop: v.timeRangeStop)\r\n  |> filter(fn: (r) => r[\"_measurement\"] == \"hourly_weather\")\r\n  |> filter(fn: (r) => r[\"_field\"] == \"visibility\")\r\n  |> aggregateWindow(every: v.windowPeriod, fn: last, createEmpty: false)\r\n  |> yield(name: \"last\")",
          "refId": "A"
        }
      ],
      "timeFrom": "1h",
      "title": "Visibility",
      "type": "stat"
    },
    {
      "datasource": {
        "type": "influxdb",
        "uid": "bdr06l9c4j474b"
      },
      "fieldConfig": {
        "defaults": {
          "color": {
            "mode": "thresholds"
          },
          "mappings": [],
          "thresholds": {
            "mode": "absolute",
            "steps": [
              {
                "color": "green",
                "value": null
              }
            ]
          }
        },
        "overrides": []
      },
      "gridPos": {
        "h": 4,
        "w": 4,
        "x": 20,
        "y": 4
      },
      "hideTimeOverride": true,
      "id": 25,
      "options": {
        "colorMode": "value",
        "graphMode": "none",
        "justifyMode": "center",
        "orientation": "auto",
        "reduceOptions": {
          "calcs": [
            "lastNotNull"
          ],
          "fields": "",
          "values": false
        },
        "showPercentChange": false,
        "textMode": "auto",
        "wideLayout": true
      },
      "pluginVersion": "11.0.0",
      "targets": [
        {
          "datasource": {
            "type": "influxdb",
            "uid": "bdr06l9c4j474b"
          },
          "query": "from(bucket: \"weather\")\r\n  |> range(start: v.timeRangeStart, stop: v.timeRangeStop)\r\n  |> filter(fn: (r) => r[\"_measurement\"] == \"hourly_weather\")\r\n  |> filter(fn: (r) => r[\"_field\"] == \"uvIndex\")\r\n  |> aggregateWindow(every: v.windowPeriod, fn: last, createEmpty: false)\r\n  |> yield(name: \"last\")",
          "refId": "A"
        }
      ],
      "timeFrom": "1h",
      "title": "UV Index",
      "type": "stat"
    },
    {
      "datasource": {
        "type": "influxdb",
        "uid": "bdr06l9c4j474b"
      },
      "fieldConfig": {
        "defaults": {
          "color": {
            "mode": "thresholds"
          },
          "mappings": [],
          "thresholds": {
            "mode": "absolute",
            "steps": [
              {
                "color": "green",
                "value": null
              }
            ]
          },
          "unit": "degree"
        },
        "overrides": []
      },
      "gridPos": {
        "h": 4,
        "w": 4,
        "x": 12,
        "y": 8
      },
      "id": 8,
      "options": {
        "colorMode": "value",
        "graphMode": "none",
        "justifyMode": "center",
        "orientation": "auto",
        "reduceOptions": {
          "calcs": [
            "lastNotNull"
          ],
          "fields": "",
          "values": false
        },
        "showPercentChange": false,
        "textMode": "auto",
        "wideLayout": true
      },
      "pluginVersion": "11.0.0",
      "targets": [
        {
          "datasource": {
            "type": "influxdb",
            "uid": "bdr06l9c4j474b"
          },
          "query": "from(bucket: \"weather\")\r\n  |> range(start: v.timeRangeStart, stop: v.timeRangeStop)\r\n  |> filter(fn: (r) => r[\"_measurement\"] == \"current_weather\")\r\n  |> filter(fn: (r) => r[\"_field\"] == \"windDirection\")\r\n  |> aggregateWindow(every: v.windowPeriod, fn: last, createEmpty: false)\r\n  |> yield(name: \"last\")",
          "refId": "A"
        }
      ],
      "title": "Wind direction",
      "type": "stat"
    },
    {
      "datasource": {
        "type": "influxdb",
        "uid": "bdr06l9c4j474b"
      },
      "fieldConfig": {
        "defaults": {
          "color": {
            "mode": "thresholds"
          },
          "mappings": [],
          "thresholds": {
            "mode": "absolute",
            "steps": [
              {
                "color": "green",
                "value": null
              }
            ]
          },
          "unit": "velocitykmh"
        },
        "overrides": []
      },
      "gridPos": {
        "h": 4,
        "w": 4,
        "x": 16,
        "y": 8
      },
      "id": 7,
      "options": {
        "colorMode": "value",
        "graphMode": "none",
        "justifyMode": "center",
        "orientation": "auto",
        "reduceOptions": {
          "calcs": [
            "lastNotNull"
          ],
          "fields": "",
          "values": false
        },
        "showPercentChange": false,
        "textMode": "auto",
        "wideLayout": true
      },
      "pluginVersion": "11.0.0",
      "targets": [
        {
          "datasource": {
            "type": "influxdb",
            "uid": "bdr06l9c4j474b"
          },
          "query": "from(bucket: \"weather\")\r\n  |> range(start: v.timeRangeStart, stop: v.timeRangeStop)\r\n  |> filter(fn: (r) => r[\"_measurement\"] == \"current_weather\")\r\n  |> filter(fn: (r) => r[\"_field\"] == \"windSpeed\")\r\n  |> aggregateWindow(every: v.windowPeriod, fn: last, createEmpty: false)\r\n  |> yield(name: \"last\")",
          "refId": "A"
        }
      ],
      "title": "Wind speed",
      "type": "stat"
    },
    {
      "datasource": {
        "type": "influxdb",
        "uid": "bdr06l9c4j474b"
      },
      "fieldConfig": {
        "defaults": {
          "color": {
            "mode": "thresholds"
          },
          "mappings": [],
          "thresholds": {
            "mode": "absolute",
            "steps": [
              {
                "color": "green",
                "value": null
              }
            ]
          },
          "unit": "percent"
        },
        "overrides": []
      },
      "gridPos": {
        "h": 4,
        "w": 4,
        "x": 20,
        "y": 8
      },
      "id": 6,
      "options": {
        "colorMode": "value",
        "graphMode": "none",
        "justifyMode": "center",
        "orientation": "auto",
        "reduceOptions": {
          "calcs": [
            "lastNotNull"
          ],
          "fields": "",
          "values": false
        },
        "showPercentChange": false,
        "textMode": "auto",
        "wideLayout": true
      },
      "pluginVersion": "11.0.0",
      "targets": [
        {
          "datasource": {
            "type": "influxdb",
            "uid": "bdr06l9c4j474b"
          },
          "query": "from(bucket: \"weather\")\r\n  |> range(start: v.timeRangeStart, stop: v.timeRangeStop)\r\n  |> filter(fn: (r) => r[\"_measurement\"] == \"current_weather\")\r\n  |> filter(fn: (r) => r[\"_field\"] == \"cloudCover\")\r\n  |> aggregateWindow(every: v.windowPeriod, fn: last, createEmpty: false)\r\n  |> yield(name: \"last\")",
          "refId": "A"
        }
      ],
      "title": "Cloud cover",
      "type": "stat"
    },
    {
      "datasource": {
        "type": "influxdb",
        "uid": "bdr06l9c4j474b"
      },
      "fieldConfig": {
        "defaults": {
          "color": {
            "mode": "thresholds"
          },
          "mappings": [],
          "thresholds": {
            "mode": "absolute",
            "steps": [
              {
                "color": "green",
                "value": null
              }
            ]
          },
          "unit": "lengthmm"
        },
        "overrides": []
      },
      "gridPos": {
        "h": 4,
        "w": 4,
        "x": 12,
        "y": 12
      },
      "id": 5,
      "options": {
        "colorMode": "value",
        "graphMode": "none",
        "justifyMode": "center",
        "orientation": "auto",
        "reduceOptions": {
          "calcs": [
            "lastNotNull"
          ],
          "fields": "",
          "values": false
        },
        "showPercentChange": false,
        "textMode": "auto",
        "wideLayout": true
      },
      "pluginVersion": "11.0.0",
      "targets": [
        {
          "datasource": {
            "type": "influxdb",
            "uid": "bdr06l9c4j474b"
          },
          "query": "from(bucket: \"weather\")\r\n  |> range(start: v.timeRangeStart, stop: v.timeRangeStop)\r\n  |> filter(fn: (r) => r[\"_measurement\"] == \"current_weather\")\r\n  |> filter(fn: (r) => r[\"_field\"] == \"rain\")\r\n  |> aggregateWindow(every: v.windowPeriod, fn: last, createEmpty: false)\r\n  |> yield(name: \"last\")",
          "refId": "A"
        }
      ],
      "title": "Rain",
      "type": "stat"
    },
    {
      "datasource": {
        "type": "influxdb",
        "uid": "bdr06l9c4j474b"
      },
      "fieldConfig": {
        "defaults": {
          "color": {
            "mode": "thresholds"
          },
          "mappings": [],
          "thresholds": {
            "mode": "absolute",
            "steps": [
              {
                "color": "green",
                "value": null
              }
            ]
          },
          "unit": "lengthmm"
        },
        "overrides": []
      },
      "gridPos": {
        "h": 4,
        "w": 4,
        "x": 16,
        "y": 12
      },
      "id": 24,
      "options": {
        "colorMode": "value",
        "graphMode": "none",
        "justifyMode": "center",
        "orientation": "auto",
        "reduceOptions": {
          "calcs": [
            "lastNotNull"
          ],
          "fields": "",
          "values": false
        },
        "showPercentChange": false,
        "textMode": "auto",
        "wideLayout": true
      },
      "pluginVersion": "11.0.0",
      "targets": [
        {
          "datasource": {
            "type": "influxdb",
            "uid": "bdr06l9c4j474b"
          },
          "query": "from(bucket: \"weather\")\r\n  |> range(start: v.timeRangeStart, stop: v.timeRangeStop)\r\n  |> filter(fn: (r) => r[\"_measurement\"] == \"current_weather\")\r\n  |> filter(fn: (r) => r[\"_field\"] == \"showers\")\r\n  |> aggregateWindow(every: v.windowPeriod, fn: last, createEmpty: false)\r\n  |> yield(name: \"last\")",
          "refId": "A"
        }
      ],
      "title": "Showers",
      "type": "stat"
    },
    {
      "collapsed": false,
      "gridPos": {
        "h": 1,
        "w": 24,
        "x": 0,
        "y": 16
      },
      "id": 10,
      "panels": [],
      "title": "Daily",
      "type": "row"
    },
    {
      "datasource": {
        "type": "influxdb",
        "uid": "bdr06l9c4j474b"
      },
      "fieldConfig": {
        "defaults": {
          "color": {
            "mode": "palette-classic"
          },
          "custom": {
            "axisBorderShow": false,
            "axisCenteredZero": false,
            "axisColorMode": "text",
            "axisLabel": "",
            "axisPlacement": "auto",
            "fillOpacity": 80,
            "gradientMode": "none",
            "hideFrom": {
              "legend": false,
              "tooltip": false,
              "viz": false
            },
            "lineWidth": 1,
            "scaleDistribution": {
              "type": "linear"
            },
            "thresholdsStyle": {
              "mode": "off"
            }
          },
          "mappings": [],
          "thresholds": {
            "mode": "absolute",
            "steps": [
              {
                "color": "green",
                "value": null
              },
              {
                "color": "red",
                "value": 80
              }
            ]
          },
          "unit": "celsius"
        },
        "overrides": [
          {
            "matcher": {
              "id": "byName",
              "options": "maxTemperature"
            },
            "properties": [
              {
                "id": "displayName",
                "value": "Max temperature"
              }
            ]
          },
          {
            "matcher": {
              "id": "byName",
              "options": "minTemperature"
            },
            "properties": [
              {
                "id": "displayName",
                "value": "Min temperature"
              }
            ]
          }
        ]
      },
      "gridPos": {
        "h": 8,
        "w": 8,
        "x": 0,
        "y": 17
      },
      "id": 11,
      "options": {
        "barRadius": 0,
        "barWidth": 0.97,
        "fullHighlight": false,
        "groupWidth": 0.7,
        "legend": {
          "calcs": [
            "max",
            "min",
            "mean"
          ],
          "displayMode": "table",
          "placement": "bottom",
          "showLegend": true
        },
        "orientation": "auto",
        "showValue": "auto",
        "stacking": "none",
        "tooltip": {
          "maxHeight": 600,
          "mode": "multi",
          "sort": "none"
        },
        "xTickLabelRotation": 0,
        "xTickLabelSpacing": 0
      },
      "pluginVersion": "11.0.0",
      "targets": [
        {
          "datasource": {
            "type": "influxdb",
            "uid": "bdr06l9c4j474b"
          },
          "query": "from(bucket: \"weather\")\r\n  |> range(start: v.timeRangeStart, stop: v.timeRangeStop)\r\n  |> filter(fn: (r) => r[\"_measurement\"] == \"daily_weather\")\r\n  |> filter(fn: (r) => r[\"_field\"] == \"maxTemperature\" or r[\"_field\"] == \"minTemperature\")\r\n  |> aggregateWindow(every: v.windowPeriod, fn: last, createEmpty: false)\r\n  |> yield(name: \"last\")",
          "refId": "A"
        }
      ],
      "title": "Temperature",
      "type": "barchart"
    },
    {
      "datasource": {
        "type": "influxdb",
        "uid": "bdr06l9c4j474b"
      },
      "fieldConfig": {
        "defaults": {
          "color": {
            "mode": "palette-classic"
          },
          "custom": {
            "axisBorderShow": false,
            "axisCenteredZero": false,
            "axisColorMode": "text",
            "axisLabel": "",
            "axisPlacement": "auto",
            "fillOpacity": 80,
            "gradientMode": "none",
            "hideFrom": {
              "legend": false,
              "tooltip": false,
              "viz": false
            },
            "lineWidth": 1,
            "scaleDistribution": {
              "type": "linear"
            },
            "thresholdsStyle": {
              "mode": "off"
            }
          },
          "mappings": [],
          "thresholds": {
            "mode": "absolute",
            "steps": [
              {
                "color": "green",
                "value": null
              },
              {
                "color": "red",
                "value": 80
              }
            ]
          },
          "unit": "celsius"
        },
        "overrides": [
          {
            "matcher": {
              "id": "byName",
              "options": "maxApparentTemperature"
            },
            "properties": [
              {
                "id": "displayName",
                "value": "Max apparent temperature"
              }
            ]
          },
          {
            "matcher": {
              "id": "byName",
              "options": "minApparentTemperature"
            },
            "properties": [
              {
                "id": "displayName",
                "value": "Min apparent temperature"
              }
            ]
          }
        ]
      },
      "gridPos": {
        "h": 8,
        "w": 8,
        "x": 8,
        "y": 17
      },
      "id": 12,
      "options": {
        "barRadius": 0,
        "barWidth": 0.97,
        "fullHighlight": false,
        "groupWidth": 0.7,
        "legend": {
          "calcs": [
            "max",
            "min",
            "mean"
          ],
          "displayMode": "table",
          "placement": "bottom",
          "showLegend": true
        },
        "orientation": "auto",
        "showValue": "auto",
        "stacking": "none",
        "tooltip": {
          "maxHeight": 600,
          "mode": "multi",
          "sort": "none"
        },
        "xTickLabelRotation": 0,
        "xTickLabelSpacing": 0
      },
      "pluginVersion": "11.0.0",
      "targets": [
        {
          "datasource": {
            "type": "influxdb",
            "uid": "bdr06l9c4j474b"
          },
          "query": "from(bucket: \"weather\")\r\n  |> range(start: v.timeRangeStart, stop: v.timeRangeStop)\r\n  |> filter(fn: (r) => r[\"_measurement\"] == \"daily_weather\")\r\n  |> filter(fn: (r) => r[\"_field\"] == \"minApparentTemperature\" or r[\"_field\"] == \"maxApparentTemperature\")\r\n  |> aggregateWindow(every: v.windowPeriod, fn: last, createEmpty: false)\r\n  |> yield(name: \"last\")",
          "refId": "A"
        }
      ],
      "title": "Apparent temperature",
      "type": "barchart"
    },
    {
      "datasource": {
        "type": "influxdb",
        "uid": "bdr06l9c4j474b"
      },
      "fieldConfig": {
        "defaults": {
          "color": {
            "mode": "palette-classic"
          },
          "custom": {
            "axisBorderShow": false,
            "axisCenteredZero": false,
            "axisColorMode": "text",
            "axisLabel": "",
            "axisPlacement": "auto",
            "fillOpacity": 80,
            "gradientMode": "none",
            "hideFrom": {
              "legend": false,
              "tooltip": false,
              "viz": false
            },
            "lineWidth": 1,
            "scaleDistribution": {
              "type": "linear"
            },
            "thresholdsStyle": {
              "mode": "off"
            }
          },
          "mappings": [],
          "thresholds": {
            "mode": "absolute",
            "steps": [
              {
                "color": "green",
                "value": null
              },
              {
                "color": "red",
                "value": 80
              }
            ]
          }
        },
        "overrides": [
          {
            "matcher": {
              "id": "byName",
              "options": "sunrise"
            },
            "properties": [
              {
                "id": "displayName",
                "value": "Sunrise"
              }
            ]
          },
          {
            "matcher": {
              "id": "byName",
              "options": "sunset"
            },
            "properties": [
              {
                "id": "displayName",
                "value": "Sunset"
              }
            ]
          }
        ]
      },
      "gridPos": {
        "h": 8,
        "w": 8,
        "x": 16,
        "y": 17
      },
      "id": 13,
      "options": {
        "barRadius": 0,
        "barWidth": 0.97,
        "fullHighlight": false,
        "groupWidth": 0.7,
        "legend": {
          "calcs": [
            "max",
            "min",
            "mean"
          ],
          "displayMode": "table",
          "placement": "bottom",
          "showLegend": true
        },
        "orientation": "auto",
        "showValue": "auto",
        "stacking": "none",
        "tooltip": {
          "maxHeight": 600,
          "mode": "multi",
          "sort": "none"
        },
        "xTickLabelRotation": 0,
        "xTickLabelSpacing": 0
      },
      "pluginVersion": "11.0.0",
      "targets": [
        {
          "datasource": {
            "type": "influxdb",
            "uid": "bdr06l9c4j474b"
          },
          "query": "from(bucket: \"weather\")\r\n  |> range(start: v.timeRangeStart, stop: v.timeRangeStop)\r\n  |> filter(fn: (r) => r[\"_measurement\"] == \"daily_weather\")\r\n  |> filter(fn: (r) => r[\"_field\"] == \"sunrise\" or r[\"_field\"] == \"sunset\")\r\n  |> aggregateWindow(every: v.windowPeriod, fn: last, createEmpty: false)\r\n  |> yield(name: \"last\")",
          "refId": "A"
        }
      ],
      "title": "Sunrise & sunset",
      "type": "barchart"
    },
    {
      "datasource": {
        "type": "influxdb",
        "uid": "bdr06l9c4j474b"
      },
      "fieldConfig": {
        "defaults": {
          "color": {
            "mode": "thresholds"
          },
          "custom": {
            "axisBorderShow": false,
            "axisCenteredZero": false,
            "axisColorMode": "text",
            "axisLabel": "",
            "axisPlacement": "auto",
            "fillOpacity": 80,
            "gradientMode": "none",
            "hideFrom": {
              "legend": false,
              "tooltip": false,
              "viz": false
            },
            "lineWidth": 1,
            "scaleDistribution": {
              "type": "linear"
            },
            "thresholdsStyle": {
              "mode": "off"
            }
          },
          "mappings": [],
          "thresholds": {
            "mode": "absolute",
            "steps": [
              {
                "color": "green",
                "value": null
              },
              {
                "color": "yellow",
                "value": 5
              },
              {
                "color": "red",
                "value": 7
              }
            ]
          }
        },
        "overrides": [
          {
            "matcher": {
              "id": "byName",
              "options": "uvIndex"
            },
            "properties": [
              {
                "id": "displayName",
                "value": "UV Index"
              }
            ]
          }
        ]
      },
      "gridPos": {
        "h": 8,
        "w": 8,
        "x": 0,
        "y": 25
      },
      "id": 14,
      "options": {
        "barRadius": 0,
        "barWidth": 0.97,
        "fullHighlight": false,
        "groupWidth": 0.7,
        "legend": {
          "calcs": [
            "max",
            "min",
            "mean"
          ],
          "displayMode": "table",
          "placement": "bottom",
          "showLegend": true
        },
        "orientation": "auto",
        "showValue": "auto",
        "stacking": "none",
        "tooltip": {
          "maxHeight": 600,
          "mode": "multi",
          "sort": "none"
        },
        "xTickLabelRotation": 0,
        "xTickLabelSpacing": 0
      },
      "pluginVersion": "11.0.0",
      "targets": [
        {
          "datasource": {
            "type": "influxdb",
            "uid": "bdr06l9c4j474b"
          },
          "query": "from(bucket: \"weather\")\r\n  |> range(start: v.timeRangeStart, stop: v.timeRangeStop)\r\n  |> filter(fn: (r) => r[\"_measurement\"] == \"daily_weather\")\r\n  |> filter(fn: (r) => r[\"_field\"] == \"uvIndex\")\r\n  |> aggregateWindow(every: v.windowPeriod, fn: last, createEmpty: false)\r\n  |> yield(name: \"last\")",
          "refId": "A"
        }
      ],
      "title": "UV Index",
      "type": "barchart"
    },
    {
      "datasource": {
        "type": "influxdb",
        "uid": "bdr06l9c4j474b"
      },
      "fieldConfig": {
        "defaults": {
          "color": {
            "mode": "palette-classic-by-name"
          },
          "custom": {
            "axisBorderShow": false,
            "axisCenteredZero": false,
            "axisColorMode": "text",
            "axisLabel": "",
            "axisPlacement": "auto",
            "fillOpacity": 80,
            "gradientMode": "none",
            "hideFrom": {
              "legend": false,
              "tooltip": false,
              "viz": false
            },
            "lineWidth": 1,
            "scaleDistribution": {
              "type": "linear"
            },
            "thresholdsStyle": {
              "mode": "off"
            }
          },
          "mappings": [],
          "thresholds": {
            "mode": "absolute",
            "steps": [
              {
                "color": "green",
                "value": null
              }
            ]
          }
        },
        "overrides": [
          {
            "matcher": {
              "id": "byName",
              "options": "precipitation_hours"
            },
            "properties": [
              {
                "id": "displayName",
                "value": "Precipitation hours"
              },
              {
                "id": "unit",
                "value": "h"
              }
            ]
          },
          {
            "matcher": {
              "id": "byName",
              "options": "precipitation_probability_max"
            },
            "properties": [
              {
                "id": "displayName",
                "value": "Precipitation probability"
              },
              {
                "id": "unit",
                "value": "percent"
              }
            ]
          },
          {
            "matcher": {
              "id": "byName",
              "options": "rain"
            },
            "properties": [
              {
                "id": "displayName",
                "value": "Rain"
              },
              {
                "id": "unit",
                "value": "lengthmm"
              }
            ]
          },
          {
            "matcher": {
              "id": "byName",
              "options": "showers"
            },
            "properties": [
              {
                "id": "displayName",
                "value": "Showers"
              },
              {
                "id": "unit",
                "value": "lengthmm"
              }
            ]
          }
        ]
      },
      "gridPos": {
        "h": 8,
        "w": 8,
        "x": 8,
        "y": 25
      },
      "id": 15,
      "options": {
        "barRadius": 0,
        "barWidth": 0.97,
        "fullHighlight": false,
        "groupWidth": 0.7,
        "legend": {
          "calcs": [
            "max",
            "min",
            "mean"
          ],
          "displayMode": "table",
          "placement": "bottom",
          "showLegend": true
        },
        "orientation": "auto",
        "showValue": "auto",
        "stacking": "none",
        "tooltip": {
          "maxHeight": 600,
          "mode": "multi",
          "sort": "none"
        },
        "xTickLabelRotation": 0,
        "xTickLabelSpacing": 0
      },
      "pluginVersion": "11.0.0",
      "targets": [
        {
          "datasource": {
            "type": "influxdb",
            "uid": "bdr06l9c4j474b"
          },
          "query": "from(bucket: \"weather\")\r\n  |> range(start: v.timeRangeStart, stop: v.timeRangeStop)\r\n  |> filter(fn: (r) => r[\"_measurement\"] == \"daily_weather\")\r\n  |> filter(fn: (r) => r[\"_field\"] == \"rain\" or r[\"_field\"] == \"precipitation_hours\" or r[\"_field\"] == \"precipitation_probability_max\" or r[\"_field\"] == \"showers\")\r\n  |> aggregateWindow(every: v.windowPeriod, fn: last, createEmpty: false)\r\n  |> yield(name: \"last\")",
          "refId": "A"
        }
      ],
      "title": "Precipitation",
      "type": "barchart"
    },
    {
      "datasource": {
        "type": "influxdb",
        "uid": "bdr06l9c4j474b"
      },
      "fieldConfig": {
        "defaults": {
          "color": {
            "mode": "palette-classic"
          },
          "custom": {
            "axisBorderShow": false,
            "axisCenteredZero": false,
            "axisColorMode": "text",
            "axisLabel": "",
            "axisPlacement": "auto",
            "fillOpacity": 80,
            "gradientMode": "none",
            "hideFrom": {
              "legend": false,
              "tooltip": false,
              "viz": false
            },
            "lineWidth": 1,
            "scaleDistribution": {
              "type": "linear"
            },
            "thresholdsStyle": {
              "mode": "off"
            }
          },
          "mappings": [],
          "thresholds": {
            "mode": "absolute",
            "steps": [
              {
                "color": "green",
                "value": null
              }
            ]
          }
        },
        "overrides": [
          {
            "matcher": {
              "id": "byName",
              "options": "maxWindSpeed"
            },
            "properties": [
              {
                "id": "displayName",
                "value": "Wind speed"
              },
              {
                "id": "unit",
                "value": "velocitykmh"
              }
            ]
          },
          {
            "matcher": {
              "id": "byName",
              "options": "dominantWindDirection"
            },
            "properties": [
              {
                "id": "displayName",
                "value": "Wind direction"
              },
              {
                "id": "unit",
                "value": "degree"
              }
            ]
          }
        ]
      },
      "gridPos": {
        "h": 8,
        "w": 8,
        "x": 16,
        "y": 25
      },
      "id": 16,
      "options": {
        "barRadius": 0,
        "barWidth": 0.97,
        "fullHighlight": false,
        "groupWidth": 0.7,
        "legend": {
          "calcs": [
            "max",
            "min",
            "mean"
          ],
          "displayMode": "table",
          "placement": "bottom",
          "showLegend": true
        },
        "orientation": "auto",
        "showValue": "auto",
        "stacking": "none",
        "tooltip": {
          "maxHeight": 600,
          "mode": "multi",
          "sort": "none"
        },
        "xTickLabelRotation": 0,
        "xTickLabelSpacing": 0
      },
      "pluginVersion": "11.0.0",
      "targets": [
        {
          "datasource": {
            "type": "influxdb",
            "uid": "bdr06l9c4j474b"
          },
          "query": "from(bucket: \"weather\")\r\n  |> range(start: v.timeRangeStart, stop: v.timeRangeStop)\r\n  |> filter(fn: (r) => r[\"_measurement\"] == \"daily_weather\")\r\n  |> filter(fn: (r) => r[\"_field\"] == \"dominantWindDirection\" or r[\"_field\"] == \"maxWindSpeed\")\r\n  |> aggregateWindow(every: v.windowPeriod, fn: last, createEmpty: false)\r\n  |> yield(name: \"last\")",
          "refId": "A"
        }
      ],
      "title": "Wind",
      "type": "barchart"
    },
    {
      "collapsed": false,
      "gridPos": {
        "h": 1,
        "w": 24,
        "x": 0,
        "y": 33
      },
      "id": 17,
      "panels": [],
      "title": "Hourly",
      "type": "row"
    },
    {
      "datasource": {
        "type": "influxdb",
        "uid": "bdr06l9c4j474b"
      },
      "fieldConfig": {
        "defaults": {
          "color": {
            "mode": "palette-classic"
          },
          "custom": {
            "axisBorderShow": false,
            "axisCenteredZero": false,
            "axisColorMode": "text",
            "axisLabel": "",
            "axisPlacement": "auto",
            "barAlignment": 0,
            "drawStyle": "line",
            "fillOpacity": 0,
            "gradientMode": "none",
            "hideFrom": {
              "legend": false,
              "tooltip": false,
              "viz": false
            },
            "insertNulls": false,
            "lineInterpolation": "linear",
            "lineWidth": 1,
            "pointSize": 5,
            "scaleDistribution": {
              "type": "linear"
            },
            "showPoints": "auto",
            "spanNulls": false,
            "stacking": {
              "group": "A",
              "mode": "none"
            },
            "thresholdsStyle": {
              "mode": "off"
            }
          },
          "mappings": [],
          "thresholds": {
            "mode": "absolute",
            "steps": [
              {
                "color": "green",
                "value": null
              },
              {
                "color": "red",
                "value": 80
              }
            ]
          }
        },
        "overrides": [
          {
            "matcher": {
              "id": "byName",
              "options": "temperature"
            },
            "properties": [
              {
                "id": "displayName",
                "value": "Temperature"
              },
              {
                "id": "unit",
                "value": "celsius"
              }
            ]
          },
          {
            "matcher": {
              "id": "byName",
              "options": "apparentTemperature"
            },
            "properties": [
              {
                "id": "displayName",
                "value": "Apparent temperatur"
              },
              {
                "id": "unit",
                "value": "celsius"
              }
            ]
          }
        ]
      },
      "gridPos": {
        "h": 8,
        "w": 8,
        "x": 0,
        "y": 34
      },
      "id": 18,
      "options": {
        "legend": {
          "calcs": [
            "lastNotNull",
            "max",
            "min",
            "mean"
          ],
          "displayMode": "table",
          "placement": "bottom",
          "showLegend": true
        },
        "tooltip": {
          "maxHeight": 600,
          "mode": "multi",
          "sort": "none"
        }
      },
      "pluginVersion": "11.0.0",
      "targets": [
        {
          "datasource": {
            "type": "influxdb",
            "uid": "bdr06l9c4j474b"
          },
          "query": "from(bucket: \"weather\")\r\n  |> range(start: v.timeRangeStart, stop: v.timeRangeStop)\r\n  |> filter(fn: (r) => r[\"_measurement\"] == \"hourly_weather\")\r\n  |> filter(fn: (r) => r[\"_field\"] == \"apparentTemperature\" or r[\"_field\"] == \"temperature\")\r\n  |> aggregateWindow(every: v.windowPeriod, fn: last, createEmpty: false)\r\n  |> yield(name: \"last\")",
          "refId": "A"
        }
      ],
      "title": "Temperature",
      "type": "timeseries"
    },
    {
      "datasource": {
        "type": "influxdb",
        "uid": "bdr06l9c4j474b"
      },
      "fieldConfig": {
        "defaults": {
          "color": {
            "mode": "palette-classic"
          },
          "custom": {
            "axisBorderShow": false,
            "axisCenteredZero": false,
            "axisColorMode": "text",
            "axisLabel": "",
            "axisPlacement": "auto",
            "barAlignment": 0,
            "drawStyle": "line",
            "fillOpacity": 0,
            "gradientMode": "none",
            "hideFrom": {
              "legend": false,
              "tooltip": false,
              "viz": false
            },
            "insertNulls": false,
            "lineInterpolation": "linear",
            "lineWidth": 1,
            "pointSize": 5,
            "scaleDistribution": {
              "type": "linear"
            },
            "showPoints": "auto",
            "spanNulls": false,
            "stacking": {
              "group": "A",
              "mode": "none"
            },
            "thresholdsStyle": {
              "mode": "off"
            }
          },
          "mappings": [],
          "thresholds": {
            "mode": "absolute",
            "steps": [
              {
                "color": "yellow",
                "value": null
              },
              {
                "color": "green",
                "value": 40
              },
              {
                "color": "blue",
                "value": 60
              }
            ]
          }
        },
        "overrides": [
          {
            "matcher": {
              "id": "byName",
              "options": "humidity"
            },
            "properties": [
              {
                "id": "displayName",
                "value": "Humidity"
              },
              {
                "id": "unit",
                "value": "percent"
              }
            ]
          }
        ]
      },
      "gridPos": {
        "h": 8,
        "w": 8,
        "x": 8,
        "y": 34
      },
      "id": 19,
      "options": {
        "legend": {
          "calcs": [
            "lastNotNull",
            "max",
            "min",
            "mean"
          ],
          "displayMode": "table",
          "placement": "bottom",
          "showLegend": true
        },
        "tooltip": {
          "maxHeight": 600,
          "mode": "multi",
          "sort": "none"
        }
      },
      "pluginVersion": "11.0.0",
      "targets": [
        {
          "datasource": {
            "type": "influxdb",
            "uid": "bdr06l9c4j474b"
          },
          "query": "from(bucket: \"weather\")\r\n  |> range(start: v.timeRangeStart, stop: v.timeRangeStop)\r\n  |> filter(fn: (r) => r[\"_measurement\"] == \"hourly_weather\")\r\n  |> filter(fn: (r) => r[\"_field\"] == \"humidity\")\r\n  |> aggregateWindow(every: v.windowPeriod, fn: last, createEmpty: false)\r\n  |> yield(name: \"last\")",
          "refId": "A"
        }
      ],
      "title": "Humidity",
      "type": "timeseries"
    },
    {
      "datasource": {
        "type": "influxdb",
        "uid": "bdr06l9c4j474b"
      },
      "fieldConfig": {
        "defaults": {
          "color": {
            "mode": "palette-classic"
          },
          "custom": {
            "axisBorderShow": false,
            "axisCenteredZero": false,
            "axisColorMode": "text",
            "axisLabel": "",
            "axisPlacement": "auto",
            "barAlignment": 0,
            "drawStyle": "line",
            "fillOpacity": 0,
            "gradientMode": "none",
            "hideFrom": {
              "legend": false,
              "tooltip": false,
              "viz": false
            },
            "insertNulls": false,
            "lineInterpolation": "linear",
            "lineWidth": 1,
            "pointSize": 5,
            "scaleDistribution": {
              "type": "linear"
            },
            "showPoints": "auto",
            "spanNulls": false,
            "stacking": {
              "group": "A",
              "mode": "none"
            },
            "thresholdsStyle": {
              "mode": "off"
            }
          },
          "mappings": [],
          "thresholds": {
            "mode": "absolute",
            "steps": [
              {
                "color": "yellow",
                "value": null
              },
              {
                "color": "green",
                "value": 40
              },
              {
                "color": "blue",
                "value": 60
              }
            ]
          }
        },
        "overrides": [
          {
            "matcher": {
              "id": "byName",
              "options": "rain"
            },
            "properties": [
              {
                "id": "displayName",
                "value": "Rain"
              },
              {
                "id": "unit",
                "value": "lengthmm"
              }
            ]
          },
          {
            "matcher": {
              "id": "byName",
              "options": "precipitation_probability"
            },
            "properties": [
              {
                "id": "displayName",
                "value": "Precipitation probability"
              },
              {
                "id": "unit",
                "value": "percent"
              }
            ]
          },
          {
            "matcher": {
              "id": "byName",
              "options": "showers"
            },
            "properties": [
              {
                "id": "displayName",
                "value": "Showers"
              },
              {
                "id": "unit",
                "value": "lengthmm"
              }
            ]
          }
        ]
      },
      "gridPos": {
        "h": 8,
        "w": 8,
        "x": 16,
        "y": 34
      },
      "id": 20,
      "options": {
        "legend": {
          "calcs": [
            "lastNotNull",
            "max",
            "min",
            "mean"
          ],
          "displayMode": "table",
          "placement": "bottom",
          "showLegend": true
        },
        "tooltip": {
          "maxHeight": 600,
          "mode": "multi",
          "sort": "none"
        }
      },
      "pluginVersion": "11.0.0",
      "targets": [
        {
          "datasource": {
            "type": "influxdb",
            "uid": "bdr06l9c4j474b"
          },
          "query": "from(bucket: \"weather\")\r\n  |> range(start: v.timeRangeStart, stop: v.timeRangeStop)\r\n  |> filter(fn: (r) => r[\"_measurement\"] == \"hourly_weather\")\r\n  |> filter(fn: (r) => r[\"_field\"] == \"rain\" or r[\"_field\"] == \"showers\" or r[\"_field\"] == \"precipitation_probability\")\r\n  |> aggregateWindow(every: v.windowPeriod, fn: last, createEmpty: false)\r\n  |> yield(name: \"last\")",
          "refId": "A"
        }
      ],
      "title": "Precipitation",
      "type": "timeseries"
    },
    {
      "datasource": {
        "type": "influxdb",
        "uid": "bdr06l9c4j474b"
      },
      "fieldConfig": {
        "defaults": {
          "color": {
            "mode": "palette-classic"
          },
          "custom": {
            "axisBorderShow": false,
            "axisCenteredZero": false,
            "axisColorMode": "text",
            "axisLabel": "",
            "axisPlacement": "auto",
            "barAlignment": 0,
            "drawStyle": "line",
            "fillOpacity": 0,
            "gradientMode": "none",
            "hideFrom": {
              "legend": false,
              "tooltip": false,
              "viz": false
            },
            "insertNulls": false,
            "lineInterpolation": "linear",
            "lineWidth": 1,
            "pointSize": 5,
            "scaleDistribution": {
              "type": "linear"
            },
            "showPoints": "auto",
            "spanNulls": false,
            "stacking": {
              "group": "A",
              "mode": "none"
            },
            "thresholdsStyle": {
              "mode": "off"
            }
          },
          "mappings": [],
          "thresholds": {
            "mode": "absolute",
            "steps": [
              {
                "color": "green",
                "value": null
              },
              {
                "color": "red",
                "value": 80
              }
            ]
          }
        },
        "overrides": [
          {
            "matcher": {
              "id": "byName",
              "options": "cloudCover"
            },
            "properties": [
              {
                "id": "displayName",
                "value": "Cloud cover"
              },
              {
                "id": "unit",
                "value": "percent"
              }
            ]
          }
        ]
      },
      "gridPos": {
        "h": 8,
        "w": 8,
        "x": 0,
        "y": 42
      },
      "id": 21,
      "options": {
        "legend": {
          "calcs": [
            "lastNotNull",
            "max",
            "min",
            "mean"
          ],
          "displayMode": "table",
          "placement": "bottom",
          "showLegend": true
        },
        "tooltip": {
          "maxHeight": 600,
          "mode": "multi",
          "sort": "none"
        }
      },
      "pluginVersion": "11.0.0",
      "targets": [
        {
          "datasource": {
            "type": "influxdb",
            "uid": "bdr06l9c4j474b"
          },
          "query": "from(bucket: \"weather\")\r\n  |> range(start: v.timeRangeStart, stop: v.timeRangeStop)\r\n  |> filter(fn: (r) => r[\"_measurement\"] == \"hourly_weather\")\r\n  |> filter(fn: (r) => r[\"_field\"] == \"cloudCover\")\r\n  |> aggregateWindow(every: v.windowPeriod, fn: last, createEmpty: false)\r\n  |> yield(name: \"last\")",
          "refId": "A"
        }
      ],
      "title": "Cloud cover",
      "type": "timeseries"
    },
    {
      "datasource": {
        "type": "influxdb",
        "uid": "bdr06l9c4j474b"
      },
      "fieldConfig": {
        "defaults": {
          "color": {
            "mode": "palette-classic"
          },
          "custom": {
            "axisBorderShow": false,
            "axisCenteredZero": false,
            "axisColorMode": "text",
            "axisLabel": "",
            "axisPlacement": "auto",
            "barAlignment": 0,
            "drawStyle": "line",
            "fillOpacity": 0,
            "gradientMode": "none",
            "hideFrom": {
              "legend": false,
              "tooltip": false,
              "viz": false
            },
            "insertNulls": false,
            "lineInterpolation": "linear",
            "lineWidth": 1,
            "pointSize": 5,
            "scaleDistribution": {
              "type": "linear"
            },
            "showPoints": "auto",
            "spanNulls": false,
            "stacking": {
              "group": "A",
              "mode": "none"
            },
            "thresholdsStyle": {
              "mode": "off"
            }
          },
          "mappings": [],
          "thresholds": {
            "mode": "absolute",
            "steps": [
              {
                "color": "green",
                "value": null
              },
              {
                "color": "red",
                "value": 80
              }
            ]
          }
        },
        "overrides": [
          {
            "matcher": {
              "id": "byName",
              "options": "uvIndex"
            },
            "properties": [
              {
                "id": "displayName",
                "value": "UV Index"
              },
              {
                "id": "unit",
                "value": "none"
              }
            ]
          },
          {
            "matcher": {
              "id": "byName",
              "options": "visibility"
            },
            "properties": [
              {
                "id": "displayName",
                "value": "Visibility"
              },
              {
                "id": "unit",
                "value": "lengthkm"
              }
            ]
          }
        ]
      },
      "gridPos": {
        "h": 8,
        "w": 8,
        "x": 8,
        "y": 42
      },
      "id": 22,
      "options": {
        "legend": {
          "calcs": [
            "lastNotNull",
            "max",
            "min",
            "mean"
          ],
          "displayMode": "table",
          "placement": "bottom",
          "showLegend": true
        },
        "tooltip": {
          "maxHeight": 600,
          "mode": "multi",
          "sort": "none"
        }
      },
      "pluginVersion": "11.0.0",
      "targets": [
        {
          "datasource": {
            "type": "influxdb",
            "uid": "bdr06l9c4j474b"
          },
          "query": "from(bucket: \"weather\")\r\n  |> range(start: v.timeRangeStart, stop: v.timeRangeStop)\r\n  |> filter(fn: (r) => r[\"_measurement\"] == \"hourly_weather\")\r\n  |> filter(fn: (r) => r[\"_field\"] == \"visibility\" or r[\"_field\"] == \"uvIndex\")\r\n  |> aggregateWindow(every: v.windowPeriod, fn: last, createEmpty: false)\r\n  |> yield(name: \"last\")",
          "refId": "A"
        }
      ],
      "title": "UV Index & Visibility",
      "type": "timeseries"
    },
    {
      "datasource": {
        "type": "influxdb",
        "uid": "bdr06l9c4j474b"
      },
      "fieldConfig": {
        "defaults": {
          "color": {
            "mode": "palette-classic"
          },
          "custom": {
            "axisBorderShow": false,
            "axisCenteredZero": false,
            "axisColorMode": "text",
            "axisLabel": "",
            "axisPlacement": "auto",
            "barAlignment": 0,
            "drawStyle": "line",
            "fillOpacity": 0,
            "gradientMode": "none",
            "hideFrom": {
              "legend": false,
              "tooltip": false,
              "viz": false
            },
            "insertNulls": false,
            "lineInterpolation": "linear",
            "lineWidth": 1,
            "pointSize": 5,
            "scaleDistribution": {
              "type": "linear"
            },
            "showPoints": "auto",
            "spanNulls": false,
            "stacking": {
              "group": "A",
              "mode": "none"
            },
            "thresholdsStyle": {
              "mode": "off"
            }
          },
          "mappings": [],
          "thresholds": {
            "mode": "absolute",
            "steps": [
              {
                "color": "green",
                "value": null
              },
              {
                "color": "red",
                "value": 80
              }
            ]
          }
        },
        "overrides": [
          {
            "matcher": {
              "id": "byName",
              "options": "windSpeed"
            },
            "properties": [
              {
                "id": "displayName",
                "value": "Wiind speed"
              },
              {
                "id": "unit",
                "value": "velocitykmh"
              }
            ]
          },
          {
            "matcher": {
              "id": "byName",
              "options": "windDirection"
            },
            "properties": [
              {
                "id": "displayName",
                "value": "Wind direction"
              },
              {
                "id": "unit",
                "value": "degree"
              }
            ]
          }
        ]
      },
      "gridPos": {
        "h": 8,
        "w": 8,
        "x": 16,
        "y": 42
      },
      "id": 23,
      "options": {
        "legend": {
          "calcs": [
            "lastNotNull",
            "max",
            "min",
            "mean"
          ],
          "displayMode": "table",
          "placement": "bottom",
          "showLegend": true
        },
        "tooltip": {
          "maxHeight": 600,
          "mode": "multi",
          "sort": "none"
        }
      },
      "pluginVersion": "11.0.0",
      "targets": [
        {
          "datasource": {
            "type": "influxdb",
            "uid": "bdr06l9c4j474b"
          },
          "query": "from(bucket: \"weather\")\r\n  |> range(start: v.timeRangeStart, stop: v.timeRangeStop)\r\n  |> filter(fn: (r) => r[\"_measurement\"] == \"hourly_weather\")\r\n  |> filter(fn: (r) => r[\"_field\"] == \"windDirection\" or r[\"_field\"] == \"windSpeed\")\r\n  |> aggregateWindow(every: v.windowPeriod, fn: last, createEmpty: false)\r\n  |> yield(name: \"last\")",
          "refId": "A"
        }
      ],
      "title": "Wind speed & wind direction",
      "type": "timeseries"
    }
  ],
  "refresh": "5s",
  "schemaVersion": 39,
  "tags": [],
  "templating": {
    "list": []
  },
  "time": {
    "from": "now/w",
    "to": "now/w"
  },
  "timeRangeUpdatedDuringEditOrView": false,
  "timepicker": {},
  "timezone": "Asia/Bangkok",
  "title": "Weather",
  "uid": "fdqxln8ir591cb",
  "version": 6,
  "weekStart": ""
}